README.rst
setup.cfg
setup.py
src/vernacular/__init__.py
src/vernacular/i18nstr.py
src/vernacular/store.py
src/vernacular/translate.py
src/vernacular/utils.py
src/vernacular.egg-info/PKG-INFO
src/vernacular.egg-info/SOURCES.txt
src/vernacular.egg-info/dependency_links.txt
src/vernacular.egg-info/entry_points.txt
src/vernacular.egg-info/not-zip-safe
src/vernacular.egg-info/requires.txt
src/vernacular.egg-info/top_level.txt