Metadata-Version: 2.1
Name: vernacular
Version: 0.3
Summary: Internationalization components
Home-page: UNKNOWN
Author: Novareto GmbH & Souheil Chelfouh
Author-email: trollfot@gmail.com
Maintainer: Novareto GmbH
Maintainer-email: ck@novareto.de
License: BSD-3-Clause
Project-URL: Source Code, https://git.bg-kooperation.de/uvcreha/vernacular
Platform: UNKNOWN
Classifier: Environment :: Web Environment
Classifier: Intended Audience :: Developers
Classifier: License :: OSI Approved :: BSD License
Classifier: Operating System :: OS Independent
Classifier: Programming Language :: Python
Classifier: Topic :: Internet :: WWW/HTTP :: WSGI
Classifier: Topic :: Internet :: WWW/HTTP :: WSGI :: Application
Requires-Python: >=3.9
Provides-Extra: test
